ctmeasure/__init__.py
ctmeasure/control_magnetic_field.py
ctmeasure/control_temperature.py
ctmeasure/measure_module.py
ctmeasure-1.0.3.dist-info/METADATA
ctmeasure-1.0.3.dist-info/WHEEL
ctmeasure-1.0.3.dist-info/top_level.txt
ctmeasure-1.0.3.dist-info/RECORD
